pytoshop/__init__.py
pytoshop/blending_range.py
pytoshop/codecs.py
pytoshop/color_mode.py
pytoshop/core.py
pytoshop/docs.py
pytoshop/enums.py
pytoshop/image_data.py
pytoshop/image_resources.py
pytoshop/layers.py
pytoshop/packbits.pyx
pytoshop/path.py
pytoshop/tagged_block.py
pytoshop/util.py
pytoshop/user/__init__.py
pytoshop/user/nested_layers.py
pytoshop_fix_packbits-1.1.8.dist-info/METADATA
pytoshop_fix_packbits-1.1.8.dist-info/WHEEL
pytoshop_fix_packbits-1.1.8.dist-info/licenses/AUTHORS.rst
pytoshop_fix_packbits-1.1.8.dist-info/licenses/LICENSE
pytoshop_fix_packbits-1.1.8.dist-info/RECORD
