Metadata-Version: 2.3
Name: pytoshop-fix-packbits
Version: 1.1.8
Summary: A Python-based library to write Photoshop PSD files
Project-URL: Homepage, https://github.com/radius5-study/pytoshop-fix-packbits
Project-URL: Issues, https://github.com/radius5-study/pytoshop-fix-packbitsissues
Author-email: "original author: Michael Droettboom, modified by: radius5" <info@radius5.co.jp>
Classifier: Development Status :: 5 - Production/Stable
Classifier: Intended Audience :: Developers
Classifier: License :: OSI Approved :: BSD License
Classifier: Natural Language :: English
Requires-Dist: cython
Requires-Dist: numpy>=1.11
Requires-Dist: packbits
Requires-Dist: six
